odoo/addons/mrp_production_request/README.rst
odoo/addons/mrp_production_request/__init__.py
odoo/addons/mrp_production_request/__manifest__.py
odoo/addons/mrp_production_request/data/mrp_production_request_sequence.xml
odoo/addons/mrp_production_request/i18n/am.po
odoo/addons/mrp_production_request/i18n/ar.po
odoo/addons/mrp_production_request/i18n/bg.po
odoo/addons/mrp_production_request/i18n/bs.po
odoo/addons/mrp_production_request/i18n/ca.po
odoo/addons/mrp_production_request/i18n/ca_ES.po
odoo/addons/mrp_production_request/i18n/cs.po
odoo/addons/mrp_production_request/i18n/da.po
odoo/addons/mrp_production_request/i18n/de.po
odoo/addons/mrp_production_request/i18n/el_GR.po
odoo/addons/mrp_production_request/i18n/en_AU.po
odoo/addons/mrp_production_request/i18n/en_GB.po
odoo/addons/mrp_production_request/i18n/es.po
odoo/addons/mrp_production_request/i18n/es_AR.po
odoo/addons/mrp_production_request/i18n/es_CL.po
odoo/addons/mrp_production_request/i18n/es_CO.po
odoo/addons/mrp_production_request/i18n/es_CR.po
odoo/addons/mrp_production_request/i18n/es_DO.po
odoo/addons/mrp_production_request/i18n/es_EC.po
odoo/addons/mrp_production_request/i18n/es_ES.po
odoo/addons/mrp_production_request/i18n/es_MX.po
odoo/addons/mrp_production_request/i18n/es_PE.po
odoo/addons/mrp_production_request/i18n/es_PY.po
odoo/addons/mrp_production_request/i18n/es_VE.po
odoo/addons/mrp_production_request/i18n/et.po
odoo/addons/mrp_production_request/i18n/eu.po
odoo/addons/mrp_production_request/i18n/fa.po
odoo/addons/mrp_production_request/i18n/fi.po
odoo/addons/mrp_production_request/i18n/fr.po
odoo/addons/mrp_production_request/i18n/fr_CA.po
odoo/addons/mrp_production_request/i18n/fr_CH.po
odoo/addons/mrp_production_request/i18n/fr_FR.po
odoo/addons/mrp_production_request/i18n/gl.po
odoo/addons/mrp_production_request/i18n/gl_ES.po
odoo/addons/mrp_production_request/i18n/he.po
odoo/addons/mrp_production_request/i18n/hi.po
odoo11_addon_mrp_production_request-11.0.1.0.1.dist-info/METADATA
odoo11_addon_mrp_production_request-11.0.1.0.1.dist-info/RECORD
odoo11_addon_mrp_production_request-11.0.1.0.1.dist-info/WHEEL
odoo11_addon_mrp_production_request-11.0.1.0.1.dist-info/top_level.txt
